<?xml version="1.0" encoding="UTF-8" standalone="no"?><Queries><Query id="s1"><AggregateFunction>SUM</AggregateFunction><Hash>e327eec7762be4f937d4bdbdd8c856cd07548a189ede46f75954bb4e8afb4856</Hash><FactVariable>Quantity</FactVariable><DimensionVariables><DimensionVariable/></DimensionVariables><QueryScript>SELECT SUM(Quantity) as result FROM mergeview</QueryScript><QueryLabel>System Genrerated</QueryLabel></Query><Query id="s2"><AggregateFunction>SUM</AggregateFunction><Hash>20978021e379c1064ddec12d6f0260a97cfc378887d3f484aac4d6c3c4f57a45</Hash><FactVariable>Price</FactVariable><DimensionVariables><DimensionVariable/></DimensionVariables><QueryScript>SELECT SUM(Price) as result FROM mergeview</QueryScript><QueryLabel>System Genrerated</QueryLabel></Query><Query id="s3"><AggregateFunction>COUNT</AggregateFunction><Hash>d0571633d67fbfb1c54c54a2131c28736435469ad6018e265f3d9007598e47d2</Hash><FactVariable>Quantity</FactVariable><DimensionVariables><DimensionVariable/></DimensionVariables><QueryScript>SELECT COUNT(Quantity) as result FROM mergeview</QueryScript><QueryLabel>System Genrerated</QueryLabel></Query><Query id="s4"><AggregateFunction>COUNT</AggregateFunction><Hash>0f5f2a387d99c201d4a9cdd4f671dfc6bafcd72c3142e5783d2a8c8ff2610fb5</Hash><FactVariable>Price</FactVariable><DimensionVariables><DimensionVariable/></DimensionVariables><QueryScript>SELECT COUNT(Price) as result FROM mergeview</QueryScript><QueryLabel>System Genrerated</QueryLabel></Query><Query id="s5"><AggregateFunction>AVG</AggregateFunction><Hash>93e694aa3142f1abe1dca70fc41afff0326f7708a208421f4f89fba9211a8117</Hash><FactVariable>Quantity</FactVariable><DimensionVariables><DimensionVariable/></DimensionVariables><QueryScript>SELECT AVG(Quantity) as result FROM mergeview</QueryScript><QueryLabel>System Genrerated</QueryLabel></Query><Query id="s6"><AggregateFunction>AVG</AggregateFunction><Hash>361368a03bb5553b847569d654f1b1660e6c4cd9d20e0fbe586fffa2eb403fa5</Hash><FactVariable>Price</FactVariable><DimensionVariables><DimensionVariable/></DimensionVariables><QueryScript>SELECT AVG(Price) as result FROM mergeview</QueryScript><QueryLabel>System Genrerated</QueryLabel></Query><Query id="s7"><AggregateFunction>MIN</AggregateFunction><Hash>7bc6babf6b311cecbd9d3713e936efb1ef8c65b29ac03654052c311038a69e9e</Hash><FactVariable>Quantity</FactVariable><DimensionVariables><DimensionVariable/></DimensionVariables><QueryScript>SELECT MIN(Quantity) as result FROM mergeview</QueryScript><QueryLabel>System Genrerated</QueryLabel></Query><Query id="s8"><AggregateFunction>MIN</AggregateFunction><Hash>2bca952b2bfd6419ab6f462304bc41701f09ec453db5497340dbd3e785a7fe4f</Hash><FactVariable>Price</FactVariable><DimensionVariables><DimensionVariable/></DimensionVariables><QueryScript>SELECT MIN(Price) as result FROM mergeview</QueryScript><QueryLabel>System Genrerated</QueryLabel></Query><Query id="s9"><AggregateFunction>MAX</AggregateFunction><Hash>2799fb621e7ec4aa3e1ffc6f12612775f7e5cce570d9c584c5ee0773697cb9c9</Hash><FactVariable>Quantity</FactVariable><DimensionVariables><DimensionVariable/></DimensionVariables><QueryScript>SELECT MAX(Quantity) as result FROM mergeview</QueryScript><QueryLabel>System Genrerated</QueryLabel></Query><Query id="s10"><AggregateFunction>MAX</AggregateFunction><Hash>b03b489c7941a37ec9e18c885fd660396cd1653634dcac1e0d9db97585248ad5</Hash><FactVariable>Price</FactVariable><DimensionVariables><DimensionVariable/></DimensionVariables><QueryScript>SELECT MAX(Price) as result FROM mergeview</QueryScript><QueryLabel>System Genrerated</QueryLabel></Query><Query id="s11"><AggregateFunction>SUM</AggregateFunction><Hash>bbd9d8bf32f25c1a1fc93f3bb740c24328ae66242ffeea229e78378e14fc28e0</Hash><FactVariable>Quantity</FactVariable><DimensionVariables><DimensionVariable>TickerSector</DimensionVariable></DimensionVariables><QueryScript>SELECT TickerSector, SUM(Quantity) as result FROM mergeview GROUP BY TickerSector</QueryScript><QueryLabel>System Genrerated</QueryLabel></Query><Query id="s12"><AggregateFunction>SUM</AggregateFunction><Hash>d2288c1cd78f8f0397c13dceefc1385c801a3f9f80e592fa2793b1ad1cc9b78b</Hash><FactVariable>Price</FactVariable><DimensionVariables><DimensionVariable>TickerSector</DimensionVariable></DimensionVariables><QueryScript>SELECT TickerSector, SUM(Price) as result FROM mergeview GROUP BY TickerSector</QueryScript><QueryLabel>System Genrerated</QueryLabel></Query><Query id="s13"><AggregateFunction>COUNT</AggregateFunction><Hash>a45f2536080f7f322d92c6db2d99be37ee18668c443da1a46db2db6e12cbe0ab</Hash><FactVariable>Quantity</FactVariable><DimensionVariables><DimensionVariable>TickerSector</DimensionVariable></DimensionVariables><QueryScript>SELECT TickerSector, COUNT(Quantity) as result FROM mergeview GROUP BY TickerSector</QueryScript><QueryLabel>System Genrerated</QueryLabel></Query><Query id="s14"><AggregateFunction>COUNT</AggregateFunction><Hash>6eac090bf3b0da912034df3ebe127563ad316f47b4277c031bc45f07338eb587</Hash><FactVariable>Price</FactVariable><DimensionVariables><DimensionVariable>TickerSector</DimensionVariable></DimensionVariables><QueryScript>SELECT TickerSector, COUNT(Price) as result FROM mergeview GROUP BY TickerSector</QueryScript><QueryLabel>System Genrerated</QueryLabel></Query><Query id="s15"><AggregateFunction>AVG</AggregateFunction><Hash>d536ac97004635eee129a2cb76ef7f9215ea90801c0c2fec616552d5a6c79cba</Hash><FactVariable>Quantity</FactVariable><DimensionVariables><DimensionVariable>TickerSector</DimensionVariable></DimensionVariables><QueryScript>SELECT TickerSector, AVG(Quantity) as result FROM mergeview GROUP BY TickerSector</QueryScript><QueryLabel>System Genrerated</QueryLabel></Query><Query id="s16"><AggregateFunction>AVG</AggregateFunction><Hash>7c7eb9dce57b7290c3e88a6c270db42e691c579970eb5ae078186ff58760912d</Hash><FactVariable>Price</FactVariable><DimensionVariables><DimensionVariable>TickerSector</DimensionVariable></DimensionVariables><QueryScript>SELECT TickerSector, AVG(Price) as result FROM mergeview GROUP BY TickerSector</QueryScript><QueryLabel>System Genrerated</QueryLabel></Query><Query id="s17"><AggregateFunction>MIN</AggregateFunction><Hash>cdebee88f6349d03ce6beb3ddccc93f15a65e323d2aaafb077cca4c89c6ce1e8</Hash><FactVariable>Quantity</FactVariable><DimensionVariables><DimensionVariable>TickerSector</DimensionVariable></DimensionVariables><QueryScript>SELECT TickerSector, MIN(Quantity) as result FROM mergeview GROUP BY TickerSector</QueryScript><QueryLabel>System Genrerated</QueryLabel></Query><Query id="s18"><AggregateFunction>MIN</AggregateFunction><Hash>e4db8001282ad6ee1db7ec18036f29ce69927700c4546c82628a25c14d3ed91c</Hash><FactVariable>Price</FactVariable><DimensionVariables><DimensionVariable>TickerSector</DimensionVariable></DimensionVariables><QueryScript>SELECT TickerSector, MIN(Price) as result FROM mergeview GROUP BY TickerSector</QueryScript><QueryLabel>System Genrerated</QueryLabel></Query><Query id="s19"><AggregateFunction>MAX</AggregateFunction><Hash>c2f8d56cab009fbb4f58c634e357cb2c421fada3afc4b2122f6df6eaa5d646f4</Hash><FactVariable>Quantity</FactVariable><DimensionVariables><DimensionVariable>TickerSector</DimensionVariable></DimensionVariables><QueryScript>SELECT TickerSector, MAX(Quantity) as result FROM mergeview GROUP BY TickerSector</QueryScript><QueryLabel>System Genrerated</QueryLabel></Query><Query id="s20"><AggregateFunction>MAX</AggregateFunction><Hash>9ea7f4722f7f9c9132200e547e12656342a053d4354c9fad30fb54f93fe9b096</Hash><FactVariable>Price</FactVariable><DimensionVariables><DimensionVariable>TickerSector</DimensionVariable></DimensionVariables><QueryScript>SELECT TickerSector, MAX(Price) as result FROM mergeview GROUP BY TickerSector</QueryScript><QueryLabel>System Genrerated</QueryLabel></Query><Query id="s21"><AggregateFunction>SUM</AggregateFunction><Hash>f3e0cab55497ea02c864d6bcaecb00d28b3f0cfa10b9377be1414386ca4dec5d</Hash><FactVariable>Quantity</FactVariable><DimensionVariables><DimensionVariable>TickerSymbol</DimensionVariable></DimensionVariables><QueryScript>SELECT TickerSymbol, SUM(Quantity) as result FROM mergeview GROUP BY TickerSymbol</QueryScript><QueryLabel>System Genrerated</QueryLabel></Query><Query id="s22"><AggregateFunction>SUM</AggregateFunction><Hash>64795b4bb107259359c627d915f55368b55e85d9d11ad691b0daf8f9bc29cda9</Hash><FactVariable>Price</FactVariable><DimensionVariables><DimensionVariable>TickerSymbol</DimensionVariable></DimensionVariables><QueryScript>SELECT TickerSymbol, SUM(Price) as result FROM mergeview GROUP BY TickerSymbol</QueryScript><QueryLabel>System Genrerated</QueryLabel></Query><Query id="s23"><AggregateFunction>COUNT</AggregateFunction><Hash>4b99207ba839c1a6b258071658c204adf6d1320a97ed3a65b06afbbc60f21009</Hash><FactVariable>Quantity</FactVariable><DimensionVariables><DimensionVariable>TickerSymbol</DimensionVariable></DimensionVariables><QueryScript>SELECT TickerSymbol, COUNT(Quantity) as result FROM mergeview GROUP BY TickerSymbol</QueryScript><QueryLabel>System Genrerated</QueryLabel></Query><Query id="s24"><AggregateFunction>COUNT</AggregateFunction><Hash>91d86d5373999fb0efabbdf4819ad25543158123674385ffe2ed8989cc8f2bb5</Hash><FactVariable>Price</FactVariable><DimensionVariables><DimensionVariable>TickerSymbol</DimensionVariable></DimensionVariables><QueryScript>SELECT TickerSymbol, COUNT(Price) as result FROM mergeview GROUP BY TickerSymbol</QueryScript><QueryLabel>System Genrerated</QueryLabel></Query><Query id="s25"><AggregateFunction>AVG</AggregateFunction><Hash>6c4d3e6d89b3b948640f8da65c0aeab168fc58fb572a8b1e5c2a24ad08afb654</Hash><FactVariable>Quantity</FactVariable><DimensionVariables><DimensionVariable>TickerSymbol</DimensionVariable></DimensionVariables><QueryScript>SELECT TickerSymbol, AVG(Quantity) as result FROM mergeview GROUP BY TickerSymbol</QueryScript><QueryLabel>System Genrerated</QueryLabel></Query><Query id="s26"><AggregateFunction>AVG</AggregateFunction><Hash>404be18024d6dc94cfd74074baf17a0019eb19c0fcb78ff4cde77f706cb1d030</Hash><FactVariable>Price</FactVariable><DimensionVariables><DimensionVariable>TickerSymbol</DimensionVariable></DimensionVariables><QueryScript>SELECT TickerSymbol, AVG(Price) as result FROM mergeview GROUP BY TickerSymbol</QueryScript><QueryLabel>System Genrerated</QueryLabel></Query><Query id="s27"><AggregateFunction>MIN</AggregateFunction><Hash>671b8c0320d0ee706b55d565c503daf5172b2c2c573938de89ef327b0c9b0a24</Hash><FactVariable>Quantity</FactVariable><DimensionVariables><DimensionVariable>TickerSymbol</DimensionVariable></DimensionVariables><QueryScript>SELECT TickerSymbol, MIN(Quantity) as result FROM mergeview GROUP BY TickerSymbol</QueryScript><QueryLabel>System Genrerated</QueryLabel></Query><Query id="s28"><AggregateFunction>MIN</AggregateFunction><Hash>79fee1a90cf9280d43cba8137d6a73be0f60b20d26b33f1462c18c902ee35a21</Hash><FactVariable>Price</FactVariable><DimensionVariables><DimensionVariable>TickerSymbol</DimensionVariable></DimensionVariables><QueryScript>SELECT TickerSymbol, MIN(Price) as result FROM mergeview GROUP BY TickerSymbol</QueryScript><QueryLabel>System Genrerated</QueryLabel></Query><Query id="s29"><AggregateFunction>MAX</AggregateFunction><Hash>0f358e147431ba2c3b2b05a41befd559597552aa25cca86e47f0472329162c13</Hash><FactVariable>Quantity</FactVariable><DimensionVariables><DimensionVariable>TickerSymbol</DimensionVariable></DimensionVariables><QueryScript>SELECT TickerSymbol, MAX(Quantity) as result FROM mergeview GROUP BY TickerSymbol</QueryScript><QueryLabel>System Genrerated</QueryLabel></Query><Query id="s30"><AggregateFunction>MAX</AggregateFunction><Hash>02d0cc0f6cb7c853c827b2cafb49ba70270a7abb9a80dce35a5fd0a9f0c1a49a</Hash><FactVariable>Price</FactVariable><DimensionVariables><DimensionVariable>TickerSymbol</DimensionVariable></DimensionVariables><QueryScript>SELECT TickerSymbol, MAX(Price) as result FROM mergeview GROUP BY TickerSymbol</QueryScript><QueryLabel>System Genrerated</QueryLabel></Query><Query id="s31"><AggregateFunction>SUM</AggregateFunction><Hash>f0ba597c89587d1122c7dd2093d5ca69cde5f7963364f3fa4ce8d21ad0c713e2</Hash><FactVariable>Quantity</FactVariable><DimensionVariables><DimensionVariable>TickerSector</DimensionVariable><DimensionVariable>TickerSymbol</DimensionVariable></DimensionVariables><QueryScript>SELECT TickerSector,TickerSymbol, SUM(Quantity) as result FROM mergeview GROUP BY TickerSector,TickerSymbol</QueryScript><QueryLabel>System Genrerated</QueryLabel></Query><Query id="s32"><AggregateFunction>SUM</AggregateFunction><Hash>27185dee6ce140fc2c78ca3e7caf6b5fe36b55125eb8b903caf1548ee394a1aa</Hash><FactVariable>Price</FactVariable><DimensionVariables><DimensionVariable>TickerSector</DimensionVariable><DimensionVariable>TickerSymbol</DimensionVariable></DimensionVariables><QueryScript>SELECT TickerSector,TickerSymbol, SUM(Price) as result FROM mergeview GROUP BY TickerSector,TickerSymbol</QueryScript><QueryLabel>System Genrerated</QueryLabel></Query><Query id="s33"><AggregateFunction>COUNT</AggregateFunction><Hash>9dce76cbc7ada2eb982abaa346c6088455e8cf3a27440342a7f83436704b7509</Hash><FactVariable>Quantity</FactVariable><DimensionVariables><DimensionVariable>TickerSector</DimensionVariable><DimensionVariable>TickerSymbol</DimensionVariable></DimensionVariables><QueryScript>SELECT TickerSector,TickerSymbol, COUNT(Quantity) as result FROM mergeview GROUP BY TickerSector,TickerSymbol</QueryScript><QueryLabel>System Genrerated</QueryLabel></Query><Query id="s34"><AggregateFunction>COUNT</AggregateFunction><Hash>0c5bb5c043366c55f48fa0efb1aec9fb0f6d01a63ca5e94a1dab39ebb5a82ae4</Hash><FactVariable>Price</FactVariable><DimensionVariables><DimensionVariable>TickerSector</DimensionVariable><DimensionVariable>TickerSymbol</DimensionVariable></DimensionVariables><QueryScript>SELECT TickerSector,TickerSymbol, COUNT(Price) as result FROM mergeview GROUP BY TickerSector,TickerSymbol</QueryScript><QueryLabel>System Genrerated</QueryLabel></Query><Query id="s35"><AggregateFunction>AVG</AggregateFunction><Hash>0476113ba294d4a5d75873b06ffa0a37b4c2a23c6687526c67dc8b5c04b3d602</Hash><FactVariable>Quantity</FactVariable><DimensionVariables><DimensionVariable>TickerSector</DimensionVariable><DimensionVariable>TickerSymbol</DimensionVariable></DimensionVariables><QueryScript>SELECT TickerSector,TickerSymbol, AVG(Quantity) as result FROM mergeview GROUP BY TickerSector,TickerSymbol</QueryScript><QueryLabel>System Genrerated</QueryLabel></Query><Query id="s36"><AggregateFunction>AVG</AggregateFunction><Hash>cf4141da3cb9f2b7e3b377266c7590499750b00c6b25cf00f16837af89327013</Hash><FactVariable>Price</FactVariable><DimensionVariables><DimensionVariable>TickerSector</DimensionVariable><DimensionVariable>TickerSymbol</DimensionVariable></DimensionVariables><QueryScript>SELECT TickerSector,TickerSymbol, AVG(Price) as result FROM mergeview GROUP BY TickerSector,TickerSymbol</QueryScript><QueryLabel>System Genrerated</QueryLabel></Query><Query id="s37"><AggregateFunction>MIN</AggregateFunction><Hash>db2d34a03ac6a9752c7e5935d167a4468ce726fd0363a5e823073b8b7a51bc18</Hash><FactVariable>Quantity</FactVariable><DimensionVariables><DimensionVariable>TickerSector</DimensionVariable><DimensionVariable>TickerSymbol</DimensionVariable></DimensionVariables><QueryScript>SELECT TickerSector,TickerSymbol, MIN(Quantity) as result FROM mergeview GROUP BY TickerSector,TickerSymbol</QueryScript><QueryLabel>System Genrerated</QueryLabel></Query><Query id="s38"><AggregateFunction>MIN</AggregateFunction><Hash>15caba04fd1d06b781747bd1e6aa2759975f181c3334f3ac023189996d864acb</Hash><FactVariable>Price</FactVariable><DimensionVariables><DimensionVariable>TickerSector</DimensionVariable><DimensionVariable>TickerSymbol</DimensionVariable></DimensionVariables><QueryScript>SELECT TickerSector,TickerSymbol, MIN(Price) as result FROM mergeview GROUP BY TickerSector,TickerSymbol</QueryScript><QueryLabel>System Genrerated</QueryLabel></Query><Query id="s39"><AggregateFunction>MAX</AggregateFunction><Hash>16eaa81e29536b5485bf6ff87af3d374dadacc2effed97cc7341e5bb9674f479</Hash><FactVariable>Quantity</FactVariable><DimensionVariables><DimensionVariable>TickerSector</DimensionVariable><DimensionVariable>TickerSymbol</DimensionVariable></DimensionVariables><QueryScript>SELECT TickerSector,TickerSymbol, MAX(Quantity) as result FROM mergeview GROUP BY TickerSector,TickerSymbol</QueryScript><QueryLabel>System Genrerated</QueryLabel></Query><Query id="s40"><AggregateFunction>MAX</AggregateFunction><Hash>be859c236bbf44f9830f1c1b18aa97b9b8c5240c78f28097ce5200970e68b077</Hash><FactVariable>Price</FactVariable><DimensionVariables><DimensionVariable>TickerSector</DimensionVariable><DimensionVariable>TickerSymbol</DimensionVariable></DimensionVariables><QueryScript>SELECT TickerSector,TickerSymbol, MAX(Price) as result FROM mergeview GROUP BY TickerSector,TickerSymbol</QueryScript><QueryLabel>System Genrerated</QueryLabel></Query><Query id="s41"><AggregateFunction>SUM</AggregateFunction><Hash>9c084084cbd629eb39dc7eb9820dec3abcb1a80d19fb31e310c362a6433229b6</Hash><FactVariable>Quantity</FactVariable><DimensionVariables><DimensionVariable>TradeAction</DimensionVariable></DimensionVariables><QueryScript>SELECT TradeAction, SUM(Quantity) as result FROM mergeview GROUP BY TradeAction</QueryScript><QueryLabel>System Genrerated</QueryLabel></Query><Query id="s42"><AggregateFunction>SUM</AggregateFunction><Hash>b6409a446c55b175f8c2a3ad4752fcf2c06e8612b8becbf9b0ae03074056e852</Hash><FactVariable>Price</FactVariable><DimensionVariables><DimensionVariable>TradeAction</DimensionVariable></DimensionVariables><QueryScript>SELECT TradeAction, SUM(Price) as result FROM mergeview GROUP BY TradeAction</QueryScript><QueryLabel>System Genrerated</QueryLabel></Query><Query id="s43"><AggregateFunction>COUNT</AggregateFunction><Hash>1c21c86122c40f847953ec0639db900687c5d3b7f4cc3a7a8c2a65138ec290f2</Hash><FactVariable>Quantity</FactVariable><DimensionVariables><DimensionVariable>TradeAction</DimensionVariable></DimensionVariables><QueryScript>SELECT TradeAction, COUNT(Quantity) as result FROM mergeview GROUP BY TradeAction</QueryScript><QueryLabel>System Genrerated</QueryLabel></Query><Query id="s44"><AggregateFunction>COUNT</AggregateFunction><Hash>9e8aa4f079925e8c63255ad9dc10cfa6ebed8e9c97411cb5bd4ea95ab02d9943</Hash><FactVariable>Price</FactVariable><DimensionVariables><DimensionVariable>TradeAction</DimensionVariable></DimensionVariables><QueryScript>SELECT TradeAction, COUNT(Price) as result FROM mergeview GROUP BY TradeAction</QueryScript><QueryLabel>System Genrerated</QueryLabel></Query><Query id="s45"><AggregateFunction>AVG</AggregateFunction><Hash>e3c653ee5bdfcf0f0af3b47acca778af65ef16c93578acdb6259bd1ed24f8c36</Hash><FactVariable>Quantity</FactVariable><DimensionVariables><DimensionVariable>TradeAction</DimensionVariable></DimensionVariables><QueryScript>SELECT TradeAction, AVG(Quantity) as result FROM mergeview GROUP BY TradeAction</QueryScript><QueryLabel>System Genrerated</QueryLabel></Query><Query id="s46"><AggregateFunction>AVG</AggregateFunction><Hash>b4d748eed9a3ba13c42d45b8419e88ce7c955d6945378785dac575ff72467fc4</Hash><FactVariable>Price</FactVariable><DimensionVariables><DimensionVariable>TradeAction</DimensionVariable></DimensionVariables><QueryScript>SELECT TradeAction, AVG(Price) as result FROM mergeview GROUP BY TradeAction</QueryScript><QueryLabel>System Genrerated</QueryLabel></Query><Query id="s47"><AggregateFunction>MIN</AggregateFunction><Hash>47ac18da0e9b02e8adc67c49c17d06b7e190c2c36e45d47ab7ca73c9b09713ce</Hash><FactVariable>Quantity</FactVariable><DimensionVariables><DimensionVariable>TradeAction</DimensionVariable></DimensionVariables><QueryScript>SELECT TradeAction, MIN(Quantity) as result FROM mergeview GROUP BY TradeAction</QueryScript><QueryLabel>System Genrerated</QueryLabel></Query><Query id="s48"><AggregateFunction>MIN</AggregateFunction><Hash>3be9377a788e161ac28eabf6ae20f35ef0620d948ccec68306f275b382b703a0</Hash><FactVariable>Price</FactVariable><DimensionVariables><DimensionVariable>TradeAction</DimensionVariable></DimensionVariables><QueryScript>SELECT TradeAction, MIN(Price) as result FROM mergeview GROUP BY TradeAction</QueryScript><QueryLabel>System Genrerated</QueryLabel></Query><Query id="s49"><AggregateFunction>MAX</AggregateFunction><Hash>e1e7806478adf514eb95c0c674bd1d242abf594ad52e94ee485194a5d5c5b3bd</Hash><FactVariable>Quantity</FactVariable><DimensionVariables><DimensionVariable>TradeAction</DimensionVariable></DimensionVariables><QueryScript>SELECT TradeAction, MAX(Quantity) as result FROM mergeview GROUP BY TradeAction</QueryScript><QueryLabel>System Genrerated</QueryLabel></Query><Query id="s50"><AggregateFunction>MAX</AggregateFunction><Hash>b63a1f64ea405bc0b695a81b96b4b3d3aea01aa70095883241291bdde058b7b5</Hash><FactVariable>Price</FactVariable><DimensionVariables><DimensionVariable>TradeAction</DimensionVariable></DimensionVariables><QueryScript>SELECT TradeAction, MAX(Price) as result FROM mergeview GROUP BY TradeAction</QueryScript><QueryLabel>System Genrerated</QueryLabel></Query><Query id="s51"><AggregateFunction>SUM</AggregateFunction><Hash>d868f581b7a0fe90ae9f34b61b5a3a1b0583f30659e33b7d0e1fe9bca6c66317</Hash><FactVariable>Quantity</FactVariable><DimensionVariables><DimensionVariable>TickerSector</DimensionVariable><DimensionVariable>TradeAction</DimensionVariable></DimensionVariables><QueryScript>SELECT TickerSector,TradeAction, SUM(Quantity) as result FROM mergeview GROUP BY TickerSector,TradeAction</QueryScript><QueryLabel>System Genrerated</QueryLabel></Query><Query id="s52"><AggregateFunction>SUM</AggregateFunction><Hash>af564ef80a41f8e2344de79a3e11c319faa3731820d8d634c2ebfc0f42c0b97a</Hash><FactVariable>Price</FactVariable><DimensionVariables><DimensionVariable>TickerSector</DimensionVariable><DimensionVariable>TradeAction</DimensionVariable></DimensionVariables><QueryScript>SELECT TickerSector,TradeAction, SUM(Price) as result FROM mergeview GROUP BY TickerSector,TradeAction</QueryScript><QueryLabel>System Genrerated</QueryLabel></Query><Query id="s53"><AggregateFunction>COUNT</AggregateFunction><Hash>3a8de300997337e9d67a19459f0a0b12b385d6b0980d1a652384e7254150387a</Hash><FactVariable>Quantity</FactVariable><DimensionVariables><DimensionVariable>TickerSector</DimensionVariable><DimensionVariable>TradeAction</DimensionVariable></DimensionVariables><QueryScript>SELECT TickerSector,TradeAction, COUNT(Quantity) as result FROM mergeview GROUP BY TickerSector,TradeAction</QueryScript><QueryLabel>System Genrerated</QueryLabel></Query><Query id="s54"><AggregateFunction>COUNT</AggregateFunction><Hash>a2e787c7b27258831dd88a061c285d93e457886fa803006cc80df350ff683fb2</Hash><FactVariable>Price</FactVariable><DimensionVariables><DimensionVariable>TickerSector</DimensionVariable><DimensionVariable>TradeAction</DimensionVariable></DimensionVariables><QueryScript>SELECT TickerSector,TradeAction, COUNT(Price) as result FROM mergeview GROUP BY TickerSector,TradeAction</QueryScript><QueryLabel>System Genrerated</QueryLabel></Query><Query id="s55"><AggregateFunction>AVG</AggregateFunction><Hash>bc4bca6099cc56cb70e486d90c9a1b677c19e3674a9a347ec1f337e97c7cf4bc</Hash><FactVariable>Quantity</FactVariable><DimensionVariables><DimensionVariable>TickerSector</DimensionVariable><DimensionVariable>TradeAction</DimensionVariable></DimensionVariables><QueryScript>SELECT TickerSector,TradeAction, AVG(Quantity) as result FROM mergeview GROUP BY TickerSector,TradeAction</QueryScript><QueryLabel>System Genrerated</QueryLabel></Query><Query id="s56"><AggregateFunction>AVG</AggregateFunction><Hash>bd7767aad67d9636d3b22ab84537de12abc9fefacb0d5e88ece77b8c26c308d8</Hash><FactVariable>Price</FactVariable><DimensionVariables><DimensionVariable>TickerSector</DimensionVariable><DimensionVariable>TradeAction</DimensionVariable></DimensionVariables><QueryScript>SELECT TickerSector,TradeAction, AVG(Price) as result FROM mergeview GROUP BY TickerSector,TradeAction</QueryScript><QueryLabel>System Genrerated</QueryLabel></Query><Query id="s57"><AggregateFunction>MIN</AggregateFunction><Hash>cdb470918913d2befbe1162ca5c2ef253df3a66e6bea2ae5719f8a2954f5357c</Hash><FactVariable>Quantity</FactVariable><DimensionVariables><DimensionVariable>TickerSector</DimensionVariable><DimensionVariable>TradeAction</DimensionVariable></DimensionVariables><QueryScript>SELECT TickerSector,TradeAction, MIN(Quantity) as result FROM mergeview GROUP BY TickerSector,TradeAction</QueryScript><QueryLabel>System Genrerated</QueryLabel></Query><Query id="s58"><AggregateFunction>MIN</AggregateFunction><Hash>e1313d9560a2799f9678571b40652db009a0702deeeed618c7d0372f5992ce3e</Hash><FactVariable>Price</FactVariable><DimensionVariables><DimensionVariable>TickerSector</DimensionVariable><DimensionVariable>TradeAction</DimensionVariable></DimensionVariables><QueryScript>SELECT TickerSector,TradeAction, MIN(Price) as result FROM mergeview GROUP BY TickerSector,TradeAction</QueryScript><QueryLabel>System Genrerated</QueryLabel></Query><Query id="s59"><AggregateFunction>MAX</AggregateFunction><Hash>57af2a60dff860fcd37b7f22642b320d9eeaa280f8aeb840d78436260daa6e62</Hash><FactVariable>Quantity</FactVariable><DimensionVariables><DimensionVariable>TickerSector</DimensionVariable><DimensionVariable>TradeAction</DimensionVariable></DimensionVariables><QueryScript>SELECT TickerSector,TradeAction, MAX(Quantity) as result FROM mergeview GROUP BY TickerSector,TradeAction</QueryScript><QueryLabel>System Genrerated</QueryLabel></Query><Query id="s60"><AggregateFunction>MAX</AggregateFunction><Hash>2e8a46e428e511764adc787ac52d729fa62bcf148b5d41c33224e61e987a2ea4</Hash><FactVariable>Price</FactVariable><DimensionVariables><DimensionVariable>TickerSector</DimensionVariable><DimensionVariable>TradeAction</DimensionVariable></DimensionVariables><QueryScript>SELECT TickerSector,TradeAction, MAX(Price) as result FROM mergeview GROUP BY TickerSector,TradeAction</QueryScript><QueryLabel>System Genrerated</QueryLabel></Query><Query id="s61"><AggregateFunction>SUM</AggregateFunction><Hash>6d17ec134ca9705d921b3fb0716763a42f3a83dfbbc37532bbb0a9df6a6c7545</Hash><FactVariable>Quantity</FactVariable><DimensionVariables><DimensionVariable>TickerSymbol</DimensionVariable><DimensionVariable>TradeAction</DimensionVariable></DimensionVariables><QueryScript>SELECT TickerSymbol,TradeAction, SUM(Quantity) as result FROM mergeview GROUP BY TickerSymbol,TradeAction</QueryScript><QueryLabel>System Genrerated</QueryLabel></Query><Query id="s62"><AggregateFunction>SUM</AggregateFunction><Hash>59b714b54120eef14722e8d4e421b6e45520c26331b4fc9334e054495d17cd9a</Hash><FactVariable>Price</FactVariable><DimensionVariables><DimensionVariable>TickerSymbol</DimensionVariable><DimensionVariable>TradeAction</DimensionVariable></DimensionVariables><QueryScript>SELECT TickerSymbol,TradeAction, SUM(Price) as result FROM mergeview GROUP BY TickerSymbol,TradeAction</QueryScript><QueryLabel>System Genrerated</QueryLabel></Query><Query id="s63"><AggregateFunction>COUNT</AggregateFunction><Hash>7956cb4fb23969669777a8e23f795643fe8b4e65f7788deffac8646c3c7b56b2</Hash><FactVariable>Quantity</FactVariable><DimensionVariables><DimensionVariable>TickerSymbol</DimensionVariable><DimensionVariable>TradeAction</DimensionVariable></DimensionVariables><QueryScript>SELECT TickerSymbol,TradeAction, COUNT(Quantity) as result FROM mergeview GROUP BY TickerSymbol,TradeAction</QueryScript><QueryLabel>System Genrerated</QueryLabel></Query><Query id="s64"><AggregateFunction>COUNT</AggregateFunction><Hash>3611e45064a906b50cd31d847bd5437a8ba11465f9e583093d53433a9170bb8d</Hash><FactVariable>Price</FactVariable><DimensionVariables><DimensionVariable>TickerSymbol</DimensionVariable><DimensionVariable>TradeAction</DimensionVariable></DimensionVariables><QueryScript>SELECT TickerSymbol,TradeAction, COUNT(Price) as result FROM mergeview GROUP BY TickerSymbol,TradeAction</QueryScript><QueryLabel>System Genrerated</QueryLabel></Query><Query id="s65"><AggregateFunction>AVG</AggregateFunction><Hash>587e5efc69253b83c6b1abcdcdf47ea968c6cc19556e266176dece35f70820d4</Hash><FactVariable>Quantity</FactVariable><DimensionVariables><DimensionVariable>TickerSymbol</DimensionVariable><DimensionVariable>TradeAction</DimensionVariable></DimensionVariables><QueryScript>SELECT TickerSymbol,TradeAction, AVG(Quantity) as result FROM mergeview GROUP BY TickerSymbol,TradeAction</QueryScript><QueryLabel>System Genrerated</QueryLabel></Query><Query id="s66"><AggregateFunction>AVG</AggregateFunction><Hash>b889902544e18501a9c4339db6e058394467f0c431a0352a66dc8b628bb4f1cb</Hash><FactVariable>Price</FactVariable><DimensionVariables><DimensionVariable>TickerSymbol</DimensionVariable><DimensionVariable>TradeAction</DimensionVariable></DimensionVariables><QueryScript>SELECT TickerSymbol,TradeAction, AVG(Price) as result FROM mergeview GROUP BY TickerSymbol,TradeAction</QueryScript><QueryLabel>System Genrerated</QueryLabel></Query><Query id="s67"><AggregateFunction>MIN</AggregateFunction><Hash>648447826a48ccf34395384368620f3bae1871c6bd4f2680f104bbf8ed7f3d60</Hash><FactVariable>Quantity</FactVariable><DimensionVariables><DimensionVariable>TickerSymbol</DimensionVariable><DimensionVariable>TradeAction</DimensionVariable></DimensionVariables><QueryScript>SELECT TickerSymbol,TradeAction, MIN(Quantity) as result FROM mergeview GROUP BY TickerSymbol,TradeAction</QueryScript><QueryLabel>System Genrerated</QueryLabel></Query><Query id="s68"><AggregateFunction>MIN</AggregateFunction><Hash>92dac69ee369df6d5bee174a69840e61bf035252a36f3c7f6b303dc5aec810ed</Hash><FactVariable>Price</FactVariable><DimensionVariables><DimensionVariable>TickerSymbol</DimensionVariable><DimensionVariable>TradeAction</DimensionVariable></DimensionVariables><QueryScript>SELECT TickerSymbol,TradeAction, MIN(Price) as result FROM mergeview GROUP BY TickerSymbol,TradeAction</QueryScript><QueryLabel>System Genrerated</QueryLabel></Query><Query id="s69"><AggregateFunction>MAX</AggregateFunction><Hash>f4b85aaec81e6f32ad30dbfbda71832096b6d1ed831021de6d5f2807b464a5da</Hash><FactVariable>Quantity</FactVariable><DimensionVariables><DimensionVariable>TickerSymbol</DimensionVariable><DimensionVariable>TradeAction</DimensionVariable></DimensionVariables><QueryScript>SELECT TickerSymbol,TradeAction, MAX(Quantity) as result FROM mergeview GROUP BY TickerSymbol,TradeAction</QueryScript><QueryLabel>System Genrerated</QueryLabel></Query><Query id="s70"><AggregateFunction>MAX</AggregateFunction><Hash>7b1f0e81d1699ce98ff94126373b03e7b64d8901bb2da5266de5d1f99cd16497</Hash><FactVariable>Price</FactVariable><DimensionVariables><DimensionVariable>TickerSymbol</DimensionVariable><DimensionVariable>TradeAction</DimensionVariable></DimensionVariables><QueryScript>SELECT TickerSymbol,TradeAction, MAX(Price) as result FROM mergeview GROUP BY TickerSymbol,TradeAction</QueryScript><QueryLabel>System Genrerated</QueryLabel></Query><Query id="s71"><AggregateFunction>SUM</AggregateFunction><Hash>19b6a0633ce7dbf9be806792e4b4b25d22e8d9d35ddaed8c870e5fff6217e580</Hash><FactVariable>Quantity</FactVariable><DimensionVariables><DimensionVariable>TickerSector</DimensionVariable><DimensionVariable>TickerSymbol</DimensionVariable><DimensionVariable>TradeAction</DimensionVariable></DimensionVariables><QueryScript>SELECT TickerSector,TickerSymbol,TradeAction, SUM(Quantity) as result FROM mergeview GROUP BY TickerSector,TickerSymbol,TradeAction</QueryScript><QueryLabel>System Genrerated</QueryLabel></Query><Query id="s72"><AggregateFunction>SUM</AggregateFunction><Hash>3e2ff7ed377415435c2d550290b1d45b62dc9f2b81b51ed67303bdffe952f3eb</Hash><FactVariable>Price</FactVariable><DimensionVariables><DimensionVariable>TickerSector</DimensionVariable><DimensionVariable>TickerSymbol</DimensionVariable><DimensionVariable>TradeAction</DimensionVariable></DimensionVariables><QueryScript>SELECT TickerSector,TickerSymbol,TradeAction, SUM(Price) as result FROM mergeview GROUP BY TickerSector,TickerSymbol,TradeAction</QueryScript><QueryLabel>System Genrerated</QueryLabel></Query><Query id="s73"><AggregateFunction>COUNT</AggregateFunction><Hash>786a3b03307b112c617fe2298416d60dcbe0bffba246d19ab3e9adad43bd5776</Hash><FactVariable>Quantity</FactVariable><DimensionVariables><DimensionVariable>TickerSector</DimensionVariable><DimensionVariable>TickerSymbol</DimensionVariable><DimensionVariable>TradeAction</DimensionVariable></DimensionVariables><QueryScript>SELECT TickerSector,TickerSymbol,TradeAction, COUNT(Quantity) as result FROM mergeview GROUP BY TickerSector,TickerSymbol,TradeAction</QueryScript><QueryLabel>System Genrerated</QueryLabel></Query><Query id="s74"><AggregateFunction>COUNT</AggregateFunction><Hash>4224324509dfab564abc164dc961e14e8193b4160cdf51b035fcc976eb2dc606</Hash><FactVariable>Price</FactVariable><DimensionVariables><DimensionVariable>TickerSector</DimensionVariable><DimensionVariable>TickerSymbol</DimensionVariable><DimensionVariable>TradeAction</DimensionVariable></DimensionVariables><QueryScript>SELECT TickerSector,TickerSymbol,TradeAction, COUNT(Price) as result FROM mergeview GROUP BY TickerSector,TickerSymbol,TradeAction</QueryScript><QueryLabel>System Genrerated</QueryLabel></Query><Query id="s75"><AggregateFunction>AVG</AggregateFunction><Hash>a3cdd287cb0faef63e53ff1daa40e773ee9afa4fe38c5da6583ee2e70e4bf16a</Hash><FactVariable>Quantity</FactVariable><DimensionVariables><DimensionVariable>TickerSector</DimensionVariable><DimensionVariable>TickerSymbol</DimensionVariable><DimensionVariable>TradeAction</DimensionVariable></DimensionVariables><QueryScript>SELECT TickerSector,TickerSymbol,TradeAction, AVG(Quantity) as result FROM mergeview GROUP BY TickerSector,TickerSymbol,TradeAction</QueryScript><QueryLabel>System Genrerated</QueryLabel></Query><Query id="s76"><AggregateFunction>AVG</AggregateFunction><Hash>e7755acaf206110aa3b3bbe1cb221c788aa14cd89b9bf109d1c4bbc0a297bf06</Hash><FactVariable>Price</FactVariable><DimensionVariables><DimensionVariable>TickerSector</DimensionVariable><DimensionVariable>TickerSymbol</DimensionVariable><DimensionVariable>TradeAction</DimensionVariable></DimensionVariables><QueryScript>SELECT TickerSector,TickerSymbol,TradeAction, AVG(Price) as result FROM mergeview GROUP BY TickerSector,TickerSymbol,TradeAction</QueryScript><QueryLabel>System Genrerated</QueryLabel></Query><Query id="s77"><AggregateFunction>MIN</AggregateFunction><Hash>c71fab98b1422434144612c83164cdba9ad7077c19843891c7ee0a509ccca916</Hash><FactVariable>Quantity</FactVariable><DimensionVariables><DimensionVariable>TickerSector</DimensionVariable><DimensionVariable>TickerSymbol</DimensionVariable><DimensionVariable>TradeAction</DimensionVariable></DimensionVariables><QueryScript>SELECT TickerSector,TickerSymbol,TradeAction, MIN(Quantity) as result FROM mergeview GROUP BY TickerSector,TickerSymbol,TradeAction</QueryScript><QueryLabel>System Genrerated</QueryLabel></Query><Query id="s78"><AggregateFunction>MIN</AggregateFunction><Hash>bf5da4e5d8bba2d726706e0316302502986f5fba464b149a4b8b8ec7d12e8406</Hash><FactVariable>Price</FactVariable><DimensionVariables><DimensionVariable>TickerSector</DimensionVariable><DimensionVariable>TickerSymbol</DimensionVariable><DimensionVariable>TradeAction</DimensionVariable></DimensionVariables><QueryScript>SELECT TickerSector,TickerSymbol,TradeAction, MIN(Price) as result FROM mergeview GROUP BY TickerSector,TickerSymbol,TradeAction</QueryScript><QueryLabel>System Genrerated</QueryLabel></Query><Query id="s79"><AggregateFunction>MAX</AggregateFunction><Hash>572fb0e8e251a258d6258adc30503fa914575f917d45afecbbbbbe1171348050</Hash><FactVariable>Quantity</FactVariable><DimensionVariables><DimensionVariable>TickerSector</DimensionVariable><DimensionVariable>TickerSymbol</DimensionVariable><DimensionVariable>TradeAction</DimensionVariable></DimensionVariables><QueryScript>SELECT TickerSector,TickerSymbol,TradeAction, MAX(Quantity) as result FROM mergeview GROUP BY TickerSector,TickerSymbol,TradeAction</QueryScript><QueryLabel>System Genrerated</QueryLabel></Query><Query id="s80"><AggregateFunction>MAX</AggregateFunction><Hash>d91ce7fdb3bfc475f8dfef2e50775f17dacda271fb2dc1e7cf980f68ad325c62</Hash><FactVariable>Price</FactVariable><DimensionVariables><DimensionVariable>TickerSector</DimensionVariable><DimensionVariable>TickerSymbol</DimensionVariable><DimensionVariable>TradeAction</DimensionVariable></DimensionVariables><QueryScript>SELECT TickerSector,TickerSymbol,TradeAction, MAX(Price) as result FROM mergeview GROUP BY TickerSector,TickerSymbol,TradeAction</QueryScript><QueryLabel>System Genrerated</QueryLabel></Query><Query id="s81"><AggregateFunction>SUM</AggregateFunction><Hash>b67fb38f1c06d29d8f92b59d71d01d96d54813abbc711b41ab977e001d340082</Hash><FactVariable>Quantity</FactVariable><DimensionVariables><DimensionVariable>WeekDay</DimensionVariable></DimensionVariables><QueryScript>SELECT WeekDay, SUM(Quantity) as result FROM mergeview GROUP BY WeekDay</QueryScript><QueryLabel>System Genrerated</QueryLabel></Query><Query id="s82"><AggregateFunction>SUM</AggregateFunction><Hash>e8df9744e5d4384aa1007cfae96dc2833b0e78644fe1abf9d22b8887a0dd411f</Hash><FactVariable>Price</FactVariable><DimensionVariables><DimensionVariable>WeekDay</DimensionVariable></DimensionVariables><QueryScript>SELECT WeekDay, SUM(Price) as result FROM mergeview GROUP BY WeekDay</QueryScript><QueryLabel>System Genrerated</QueryLabel></Query><Query id="s83"><AggregateFunction>COUNT</AggregateFunction><Hash>c0d80f61e108f1221cfcea1f34be1f17e5b50a83e586d95c0fb54f8b788ba731</Hash><FactVariable>Quantity</FactVariable><DimensionVariables><DimensionVariable>WeekDay</DimensionVariable></DimensionVariables><QueryScript>SELECT WeekDay, COUNT(Quantity) as result FROM mergeview GROUP BY WeekDay</QueryScript><QueryLabel>System Genrerated</QueryLabel></Query><Query id="s84"><AggregateFunction>COUNT</AggregateFunction><Hash>6eeb2432be2452645277a7f265b19675c0f6ac11e84fb7c5dbb783f491cd7d67</Hash><FactVariable>Price</FactVariable><DimensionVariables><DimensionVariable>WeekDay</DimensionVariable></DimensionVariables><QueryScript>SELECT WeekDay, COUNT(Price) as result FROM mergeview GROUP BY WeekDay</QueryScript><QueryLabel>System Genrerated</QueryLabel></Query><Query id="s85"><AggregateFunction>AVG</AggregateFunction><Hash>8443ef0ba5f5b1443b726e57d855fd0512f5ea8ec3dd0069a5ad14daf89608a8</Hash><FactVariable>Quantity</FactVariable><DimensionVariables><DimensionVariable>WeekDay</DimensionVariable></DimensionVariables><QueryScript>SELECT WeekDay, AVG(Quantity) as result FROM mergeview GROUP BY WeekDay</QueryScript><QueryLabel>System Genrerated</QueryLabel></Query><Query id="s86"><AggregateFunction>AVG</AggregateFunction><Hash>d8f1d43762289a8bd6663c60b7ffbf9c6b211c0101180e4d730221e92ed8fcdb</Hash><FactVariable>Price</FactVariable><DimensionVariables><DimensionVariable>WeekDay</DimensionVariable></DimensionVariables><QueryScript>SELECT WeekDay, AVG(Price) as result FROM mergeview GROUP BY WeekDay</QueryScript><QueryLabel>System Genrerated</QueryLabel></Query><Query id="s87"><AggregateFunction>MIN</AggregateFunction><Hash>86155024543878417020fea586cce8277a965b45e30a3c1235d87e1e5cf456e2</Hash><FactVariable>Quantity</FactVariable><DimensionVariables><DimensionVariable>WeekDay</DimensionVariable></DimensionVariables><QueryScript>SELECT WeekDay, MIN(Quantity) as result FROM mergeview GROUP BY WeekDay</QueryScript><QueryLabel>System Genrerated</QueryLabel></Query><Query id="s88"><AggregateFunction>MIN</AggregateFunction><Hash>276a749f1d98bf427206e8b928f80462fdb737c190af928650bbddaf24fb8d06</Hash><FactVariable>Price</FactVariable><DimensionVariables><DimensionVariable>WeekDay</DimensionVariable></DimensionVariables><QueryScript>SELECT WeekDay, MIN(Price) as result FROM mergeview GROUP BY WeekDay</QueryScript><QueryLabel>System Genrerated</QueryLabel></Query><Query id="s89"><AggregateFunction>MAX</AggregateFunction><Hash>0c07dd835294efa2c11de631d05fef6948a8e5a876d02bab869f31dd9aeaef11</Hash><FactVariable>Quantity</FactVariable><DimensionVariables><DimensionVariable>WeekDay</DimensionVariable></DimensionVariables><QueryScript>SELECT WeekDay, MAX(Quantity) as result FROM mergeview GROUP BY WeekDay</QueryScript><QueryLabel>System Genrerated</QueryLabel></Query><Query id="s90"><AggregateFunction>MAX</AggregateFunction><Hash>6d2c6b4ca18a08ec08bfcadab949c16b8163b63845deaa5b3c6cfddef092c127</Hash><FactVariable>Price</FactVariable><DimensionVariables><DimensionVariable>WeekDay</DimensionVariable></DimensionVariables><QueryScript>SELECT WeekDay, MAX(Price) as result FROM mergeview GROUP BY WeekDay</QueryScript><QueryLabel>System Genrerated</QueryLabel></Query><Query id="s91"><AggregateFunction>SUM</AggregateFunction><Hash>f49fa9669d1591da5bababf71dc8a02b65daa014d23cb15fc22e3f8b4e00ef14</Hash><FactVariable>Quantity</FactVariable><DimensionVariables><DimensionVariable>TickerSector</DimensionVariable><DimensionVariable>WeekDay</DimensionVariable></DimensionVariables><QueryScript>SELECT TickerSector,WeekDay, SUM(Quantity) as result FROM mergeview GROUP BY TickerSector,WeekDay</QueryScript><QueryLabel>System Genrerated</QueryLabel></Query><Query id="s92"><AggregateFunction>SUM</AggregateFunction><Hash>90c4d7eac4f12469d8a46403d80ffd9b9a1c952af66219ef630059400a42c66d</Hash><FactVariable>Price</FactVariable><DimensionVariables><DimensionVariable>TickerSector</DimensionVariable><DimensionVariable>WeekDay</DimensionVariable></DimensionVariables><QueryScript>SELECT TickerSector,WeekDay, SUM(Price) as result FROM mergeview GROUP BY TickerSector,WeekDay</QueryScript><QueryLabel>System Genrerated</QueryLabel></Query><Query id="s93"><AggregateFunction>COUNT</AggregateFunction><Hash>cd1677096c18c7035f7789064c0d7e03d0b80eeb4695a0dd7f44bbf92cf6c22d</Hash><FactVariable>Quantity</FactVariable><DimensionVariables><DimensionVariable>TickerSector</DimensionVariable><DimensionVariable>WeekDay</DimensionVariable></DimensionVariables><QueryScript>SELECT TickerSector,WeekDay, COUNT(Quantity) as result FROM mergeview GROUP BY TickerSector,WeekDay</QueryScript><QueryLabel>System Genrerated</QueryLabel></Query><Query id="s94"><AggregateFunction>COUNT</AggregateFunction><Hash>ace8704231e0e35ebca2080663c7ecd2934810caf10256373bfd742a04ae6d9d</Hash><FactVariable>Price</FactVariable><DimensionVariables><DimensionVariable>TickerSector</DimensionVariable><DimensionVariable>WeekDay</DimensionVariable></DimensionVariables><QueryScript>SELECT TickerSector,WeekDay, COUNT(Price) as result FROM mergeview GROUP BY TickerSector,WeekDay</QueryScript><QueryLabel>System Genrerated</QueryLabel></Query><Query id="s95"><AggregateFunction>AVG</AggregateFunction><Hash>9b970ae4cb182471a78abae66eb28ab6905926b7e3d75b630df75302776b0975</Hash><FactVariable>Quantity</FactVariable><DimensionVariables><DimensionVariable>TickerSector</DimensionVariable><DimensionVariable>WeekDay</DimensionVariable></DimensionVariables><QueryScript>SELECT TickerSector,WeekDay, AVG(Quantity) as result FROM mergeview GROUP BY TickerSector,WeekDay</QueryScript><QueryLabel>System Genrerated</QueryLabel></Query><Query id="s96"><AggregateFunction>AVG</AggregateFunction><Hash>7298063452a159dcf3926c045a0c36ce5103aea9175887aba37ac809d77934c4</Hash><FactVariable>Price</FactVariable><DimensionVariables><DimensionVariable>TickerSector</DimensionVariable><DimensionVariable>WeekDay</DimensionVariable></DimensionVariables><QueryScript>SELECT TickerSector,WeekDay, AVG(Price) as result FROM mergeview GROUP BY TickerSector,WeekDay</QueryScript><QueryLabel>System Genrerated</QueryLabel></Query><Query id="s97"><AggregateFunction>MIN</AggregateFunction><Hash>f681010fc948e23d50458ffaeea09d7384eb41228484e66eade5c44760d58143</Hash><FactVariable>Quantity</FactVariable><DimensionVariables><DimensionVariable>TickerSector</DimensionVariable><DimensionVariable>WeekDay</DimensionVariable></DimensionVariables><QueryScript>SELECT TickerSector,WeekDay, MIN(Quantity) as result FROM mergeview GROUP BY TickerSector,WeekDay</QueryScript><QueryLabel>System Genrerated</QueryLabel></Query><Query id="s98"><AggregateFunction>MIN</AggregateFunction><Hash>f3668eb79a2c21a3e65f081ecb67d6fd864c5a14ed664bba0c4c084eb2580365</Hash><FactVariable>Price</FactVariable><DimensionVariables><DimensionVariable>TickerSector</DimensionVariable><DimensionVariable>WeekDay</DimensionVariable></DimensionVariables><QueryScript>SELECT TickerSector,WeekDay, MIN(Price) as result FROM mergeview GROUP BY TickerSector,WeekDay</QueryScript><QueryLabel>System Genrerated</QueryLabel></Query><Query id="s99"><AggregateFunction>MAX</AggregateFunction><Hash>062e16b8b58250aeef7ab7195181142eee6754814974b5fe90400cc9a51dd5e5</Hash><FactVariable>Quantity</FactVariable><DimensionVariables><DimensionVariable>TickerSector</DimensionVariable><DimensionVariable>WeekDay</DimensionVariable></DimensionVariables><QueryScript>SELECT TickerSector,WeekDay, MAX(Quantity) as result FROM mergeview GROUP BY TickerSector,WeekDay</QueryScript><QueryLabel>System Genrerated</QueryLabel></Query><Query id="s100"><AggregateFunction>MAX</AggregateFunction><Hash>e9545f0a1d2249645ba479e0452d3855e591047e64958cfd0bece628dbac4ae4</Hash><FactVariable>Price</FactVariable><DimensionVariables><DimensionVariable>TickerSector</DimensionVariable><DimensionVariable>WeekDay</DimensionVariable></DimensionVariables><QueryScript>SELECT TickerSector,WeekDay, MAX(Price) as result FROM mergeview GROUP BY TickerSector,WeekDay</QueryScript><QueryLabel>System Genrerated</QueryLabel></Query><Query id="s101"><AggregateFunction>SUM</AggregateFunction><Hash>142ed8166f989bf031a9db8cab2c5247893b9ddbff1acf1eb51d418ab5490b61</Hash><FactVariable>Quantity</FactVariable><DimensionVariables><DimensionVariable>TickerSymbol</DimensionVariable><DimensionVariable>WeekDay</DimensionVariable></DimensionVariables><QueryScript>SELECT TickerSymbol,WeekDay, SUM(Quantity) as result FROM mergeview GROUP BY TickerSymbol,WeekDay</QueryScript><QueryLabel>System Genrerated</QueryLabel></Query><Query id="s102"><AggregateFunction>SUM</AggregateFunction><Hash>28cf3aba458320d88395120ea23e7d82191b1eb4efeade58dce96029af66767d</Hash><FactVariable>Price</FactVariable><DimensionVariables><DimensionVariable>TickerSymbol</DimensionVariable><DimensionVariable>WeekDay</DimensionVariable></DimensionVariables><QueryScript>SELECT TickerSymbol,WeekDay, SUM(Price) as result FROM mergeview GROUP BY TickerSymbol,WeekDay</QueryScript><QueryLabel>System Genrerated</QueryLabel></Query><Query id="s103"><AggregateFunction>COUNT</AggregateFunction><Hash>1b5c0b675b855c1325c98fbafd2a3f28efa9345b0847866130791bb69a1363ce</Hash><FactVariable>Quantity</FactVariable><DimensionVariables><DimensionVariable>TickerSymbol</DimensionVariable><DimensionVariable>WeekDay</DimensionVariable></DimensionVariables><QueryScript>SELECT TickerSymbol,WeekDay, COUNT(Quantity) as result FROM mergeview GROUP BY TickerSymbol,WeekDay</QueryScript><QueryLabel>System Genrerated</QueryLabel></Query><Query id="s104"><AggregateFunction>COUNT</AggregateFunction><Hash>23b7e2e897ad8b67722c8ceb62323c5f864204f6b909d0a08593eea19162eb9a</Hash><FactVariable>Price</FactVariable><DimensionVariables><DimensionVariable>TickerSymbol</DimensionVariable><DimensionVariable>WeekDay</DimensionVariable></DimensionVariables><QueryScript>SELECT TickerSymbol,WeekDay, COUNT(Price) as result FROM mergeview GROUP BY TickerSymbol,WeekDay</QueryScript><QueryLabel>System Genrerated</QueryLabel></Query><Query id="s105"><AggregateFunction>AVG</AggregateFunction><Hash>b99f59b5616c92207d1272f37187ddfd2c9277b90a3d5ebe617fdd11c56b501b</Hash><FactVariable>Quantity</FactVariable><DimensionVariables><DimensionVariable>TickerSymbol</DimensionVariable><DimensionVariable>WeekDay</DimensionVariable></DimensionVariables><QueryScript>SELECT TickerSymbol,WeekDay, AVG(Quantity) as result FROM mergeview GROUP BY TickerSymbol,WeekDay</QueryScript><QueryLabel>System Genrerated</QueryLabel></Query><Query id="s106"><AggregateFunction>AVG</AggregateFunction><Hash>e6eb0e1975fb2a382cf2605fd2288e88075dfc3699d9ff74711c70d4ae8f220f</Hash><FactVariable>Price</FactVariable><DimensionVariables><DimensionVariable>TickerSymbol</DimensionVariable><DimensionVariable>WeekDay</DimensionVariable></DimensionVariables><QueryScript>SELECT TickerSymbol,WeekDay, AVG(Price) as result FROM mergeview GROUP BY TickerSymbol,WeekDay</QueryScript><QueryLabel>System Genrerated</QueryLabel></Query><Query id="s107"><AggregateFunction>MIN</AggregateFunction><Hash>ee56b7a845fe0d7e8b0d142285c8f90d24a759e404e412e91a53c41a985ad0f9</Hash><FactVariable>Quantity</FactVariable><DimensionVariables><DimensionVariable>TickerSymbol</DimensionVariable><DimensionVariable>WeekDay</DimensionVariable></DimensionVariables><QueryScript>SELECT TickerSymbol,WeekDay, MIN(Quantity) as result FROM mergeview GROUP BY TickerSymbol,WeekDay</QueryScript><QueryLabel>System Genrerated</QueryLabel></Query><Query id="s108"><AggregateFunction>MIN</AggregateFunction><Hash>efa7a2d3c3212d23abe9692420f834396cf54908e7d9b19f859ec9757b8c385b</Hash><FactVariable>Price</FactVariable><DimensionVariables><DimensionVariable>TickerSymbol</DimensionVariable><DimensionVariable>WeekDay</DimensionVariable></DimensionVariables><QueryScript>SELECT TickerSymbol,WeekDay, MIN(Price) as result FROM mergeview GROUP BY TickerSymbol,WeekDay</QueryScript><QueryLabel>System Genrerated</QueryLabel></Query><Query id="s109"><AggregateFunction>MAX</AggregateFunction><Hash>189851dfbe93ccfe93daf01340a15f7f9ecc9c86a599556a76c99f1a741a3b59</Hash><FactVariable>Quantity</FactVariable><DimensionVariables><DimensionVariable>TickerSymbol</DimensionVariable><DimensionVariable>WeekDay</DimensionVariable></DimensionVariables><QueryScript>SELECT TickerSymbol,WeekDay, MAX(Quantity) as result FROM mergeview GROUP BY TickerSymbol,WeekDay</QueryScript><QueryLabel>System Genrerated</QueryLabel></Query><Query id="s110"><AggregateFunction>MAX</AggregateFunction><Hash>0e018b725d8ce9e7ef8ace4e3cc9f4f82ef56af2b0f64ef1b4fe66bb36c13e29</Hash><FactVariable>Price</FactVariable><DimensionVariables><DimensionVariable>TickerSymbol</DimensionVariable><DimensionVariable>WeekDay</DimensionVariable></DimensionVariables><QueryScript>SELECT TickerSymbol,WeekDay, MAX(Price) as result FROM mergeview GROUP BY TickerSymbol,WeekDay</QueryScript><QueryLabel>System Genrerated</QueryLabel></Query><Query id="s111"><AggregateFunction>SUM</AggregateFunction><Hash>6193cf4a522c5445220ea99b84fd3c8091022c066c60ddbd3514770938ca491a</Hash><FactVariable>Quantity</FactVariable><DimensionVariables><DimensionVariable>TickerSector</DimensionVariable><DimensionVariable>TickerSymbol</DimensionVariable><DimensionVariable>WeekDay</DimensionVariable></DimensionVariables><QueryScript>SELECT TickerSector,TickerSymbol,WeekDay, SUM(Quantity) as result FROM mergeview GROUP BY TickerSector,TickerSymbol,WeekDay</QueryScript><QueryLabel>System Genrerated</QueryLabel></Query><Query id="s112"><AggregateFunction>SUM</AggregateFunction><Hash>2cc154989e23d90304e3daeb2172e0cb3ea3995ac2d85c4929f604673d4696a3</Hash><FactVariable>Price</FactVariable><DimensionVariables><DimensionVariable>TickerSector</DimensionVariable><DimensionVariable>TickerSymbol</DimensionVariable><DimensionVariable>WeekDay</DimensionVariable></DimensionVariables><QueryScript>SELECT TickerSector,TickerSymbol,WeekDay, SUM(Price) as result FROM mergeview GROUP BY TickerSector,TickerSymbol,WeekDay</QueryScript><QueryLabel>System Genrerated</QueryLabel></Query><Query id="s113"><AggregateFunction>COUNT</AggregateFunction><Hash>efb8dd4632f430218fac83494ca5fb0bf054a659a106f69bcac750f6464aa1b8</Hash><FactVariable>Quantity</FactVariable><DimensionVariables><DimensionVariable>TickerSector</DimensionVariable><DimensionVariable>TickerSymbol</DimensionVariable><DimensionVariable>WeekDay</DimensionVariable></DimensionVariables><QueryScript>SELECT TickerSector,TickerSymbol,WeekDay, COUNT(Quantity) as result FROM mergeview GROUP BY TickerSector,TickerSymbol,WeekDay</QueryScript><QueryLabel>System Genrerated</QueryLabel></Query><Query id="s114"><AggregateFunction>COUNT</AggregateFunction><Hash>dbbde2988e8daf5996f280560f6e8da332384c759962e71cc7fbe3d7a00530d7</Hash><FactVariable>Price</FactVariable><DimensionVariables><DimensionVariable>TickerSector</DimensionVariable><DimensionVariable>TickerSymbol</DimensionVariable><DimensionVariable>WeekDay</DimensionVariable></DimensionVariables><QueryScript>SELECT TickerSector,TickerSymbol,WeekDay, COUNT(Price) as result FROM mergeview GROUP BY TickerSector,TickerSymbol,WeekDay</QueryScript><QueryLabel>System Genrerated</QueryLabel></Query><Query id="s115"><AggregateFunction>AVG</AggregateFunction><Hash>fd7f334f3a544d58c3fc14b544f9a8d8266ad9d08a1cc59f693e1ff96f984554</Hash><FactVariable>Quantity</FactVariable><DimensionVariables><DimensionVariable>TickerSector</DimensionVariable><DimensionVariable>TickerSymbol</DimensionVariable><DimensionVariable>WeekDay</DimensionVariable></DimensionVariables><QueryScript>SELECT TickerSector,TickerSymbol,WeekDay, AVG(Quantity) as result FROM mergeview GROUP BY TickerSector,TickerSymbol,WeekDay</QueryScript><QueryLabel>System Genrerated</QueryLabel></Query><Query id="s116"><AggregateFunction>AVG</AggregateFunction><Hash>cd189d2b9c766c3df662427c83e9d13fd0df4068c5906cfca3b8b38b351d7d42</Hash><FactVariable>Price</FactVariable><DimensionVariables><DimensionVariable>TickerSector</DimensionVariable><DimensionVariable>TickerSymbol</DimensionVariable><DimensionVariable>WeekDay</DimensionVariable></DimensionVariables><QueryScript>SELECT TickerSector,TickerSymbol,WeekDay, AVG(Price) as result FROM mergeview GROUP BY TickerSector,TickerSymbol,WeekDay</QueryScript><QueryLabel>System Genrerated</QueryLabel></Query><Query id="s117"><AggregateFunction>MIN</AggregateFunction><Hash>146c1c2546a12d788800dd8c5413e5586153a862efea93d10fd1d786c420caa4</Hash><FactVariable>Quantity</FactVariable><DimensionVariables><DimensionVariable>TickerSector</DimensionVariable><DimensionVariable>TickerSymbol</DimensionVariable><DimensionVariable>WeekDay</DimensionVariable></DimensionVariables><QueryScript>SELECT TickerSector,TickerSymbol,WeekDay, MIN(Quantity) as result FROM mergeview GROUP BY TickerSector,TickerSymbol,WeekDay</QueryScript><QueryLabel>System Genrerated</QueryLabel></Query><Query id="s118"><AggregateFunction>MIN</AggregateFunction><Hash>9a56ff3bd71cdc4e60b5d48f3dfc49c2cc9ca5fc36e17f43d2a0d2fc98cfafcb</Hash><FactVariable>Price</FactVariable><DimensionVariables><DimensionVariable>TickerSector</DimensionVariable><DimensionVariable>TickerSymbol</DimensionVariable><DimensionVariable>WeekDay</DimensionVariable></DimensionVariables><QueryScript>SELECT TickerSector,TickerSymbol,WeekDay, MIN(Price) as result FROM mergeview GROUP BY TickerSector,TickerSymbol,WeekDay</QueryScript><QueryLabel>System Genrerated</QueryLabel></Query><Query id="s119"><AggregateFunction>MAX</AggregateFunction><Hash>2f00d168eb18669c9c883259b7d10a235ccc2d7ed20e3f39a88d29671396abd6</Hash><FactVariable>Quantity</FactVariable><DimensionVariables><DimensionVariable>TickerSector</DimensionVariable><DimensionVariable>TickerSymbol</DimensionVariable><DimensionVariable>WeekDay</DimensionVariable></DimensionVariables><QueryScript>SELECT TickerSector,TickerSymbol,WeekDay, MAX(Quantity) as result FROM mergeview GROUP BY TickerSector,TickerSymbol,WeekDay</QueryScript><QueryLabel>System Genrerated</QueryLabel></Query><Query id="s120"><AggregateFunction>MAX</AggregateFunction><Hash>e594608d155067fabbdc1aad55af5478f9568c790637699c2301e345a3198565</Hash><FactVariable>Price</FactVariable><DimensionVariables><DimensionVariable>TickerSector</DimensionVariable><DimensionVariable>TickerSymbol</DimensionVariable><DimensionVariable>WeekDay</DimensionVariable></DimensionVariables><QueryScript>SELECT TickerSector,TickerSymbol,WeekDay, MAX(Price) as result FROM mergeview GROUP BY TickerSector,TickerSymbol,WeekDay</QueryScript><QueryLabel>System Genrerated</QueryLabel></Query><Query id="s121"><AggregateFunction>SUM</AggregateFunction><Hash>3773ec253e66b3578d2a2db3d451c72bb03e0d927a520891bbaab994851d6b57</Hash><FactVariable>Quantity</FactVariable><DimensionVariables><DimensionVariable>TradeAction</DimensionVariable><DimensionVariable>WeekDay</DimensionVariable></DimensionVariables><QueryScript>SELECT TradeAction,WeekDay, SUM(Quantity) as result FROM mergeview GROUP BY TradeAction,WeekDay</QueryScript><QueryLabel>System Genrerated</QueryLabel></Query><Query id="s122"><AggregateFunction>SUM</AggregateFunction><Hash>b311632c765c6c7872ea2d8391594ba3d6c8250952e368ab2062ac929e2c8f7a</Hash><FactVariable>Price</FactVariable><DimensionVariables><DimensionVariable>TradeAction</DimensionVariable><DimensionVariable>WeekDay</DimensionVariable></DimensionVariables><QueryScript>SELECT TradeAction,WeekDay, SUM(Price) as result FROM mergeview GROUP BY TradeAction,WeekDay</QueryScript><QueryLabel>System Genrerated</QueryLabel></Query><Query id="s123"><AggregateFunction>COUNT</AggregateFunction><Hash>8a5193481820ac7a7836d81d19c045be45e028cc1d0f7f79d96ded6e574df87f</Hash><FactVariable>Quantity</FactVariable><DimensionVariables><DimensionVariable>TradeAction</DimensionVariable><DimensionVariable>WeekDay</DimensionVariable></DimensionVariables><QueryScript>SELECT TradeAction,WeekDay, COUNT(Quantity) as result FROM mergeview GROUP BY TradeAction,WeekDay</QueryScript><QueryLabel>System Genrerated</QueryLabel></Query><Query id="s124"><AggregateFunction>COUNT</AggregateFunction><Hash>35dc60cb358881c347fcdde87eb3ad63b1adf2ad7e574cd3b5e69d699ddc021c</Hash><FactVariable>Price</FactVariable><DimensionVariables><DimensionVariable>TradeAction</DimensionVariable><DimensionVariable>WeekDay</DimensionVariable></DimensionVariables><QueryScript>SELECT TradeAction,WeekDay, COUNT(Price) as result FROM mergeview GROUP BY TradeAction,WeekDay</QueryScript><QueryLabel>System Genrerated</QueryLabel></Query><Query id="s125"><AggregateFunction>AVG</AggregateFunction><Hash>cd7e17df9d50bc457e100db256c0259e042243cc0db105b4a87f87953c75c9b7</Hash><FactVariable>Quantity</FactVariable><DimensionVariables><DimensionVariable>TradeAction</DimensionVariable><DimensionVariable>WeekDay</DimensionVariable></DimensionVariables><QueryScript>SELECT TradeAction,WeekDay, AVG(Quantity) as result FROM mergeview GROUP BY TradeAction,WeekDay</QueryScript><QueryLabel>System Genrerated</QueryLabel></Query><Query id="s126"><AggregateFunction>AVG</AggregateFunction><Hash>cb1eb90d324ae1389e1cea81ea77d3f46a60a263ad8af1fd46753b626fd0ce7f</Hash><FactVariable>Price</FactVariable><DimensionVariables><DimensionVariable>TradeAction</DimensionVariable><DimensionVariable>WeekDay</DimensionVariable></DimensionVariables><QueryScript>SELECT TradeAction,WeekDay, AVG(Price) as result FROM mergeview GROUP BY TradeAction,WeekDay</QueryScript><QueryLabel>System Genrerated</QueryLabel></Query><Query id="s127"><AggregateFunction>MIN</AggregateFunction><Hash>116f5f527a2c8445feb23e7e1ba34827a6ae250ed2f5fed398562f2be5473962</Hash><FactVariable>Quantity</FactVariable><DimensionVariables><DimensionVariable>TradeAction</DimensionVariable><DimensionVariable>WeekDay</DimensionVariable></DimensionVariables><QueryScript>SELECT TradeAction,WeekDay, MIN(Quantity) as result FROM mergeview GROUP BY TradeAction,WeekDay</QueryScript><QueryLabel>System Genrerated</QueryLabel></Query><Query id="s128"><AggregateFunction>MIN</AggregateFunction><Hash>f506d271b1f11334ff27fe9d086e3e56f6011c5e67137880fc3b2b8934657355</Hash><FactVariable>Price</FactVariable><DimensionVariables><DimensionVariable>TradeAction</DimensionVariable><DimensionVariable>WeekDay</DimensionVariable></DimensionVariables><QueryScript>SELECT TradeAction,WeekDay, MIN(Price) as result FROM mergeview GROUP BY TradeAction,WeekDay</QueryScript><QueryLabel>System Genrerated</QueryLabel></Query><Query id="s129"><AggregateFunction>MAX</AggregateFunction><Hash>1291624ec7c172d3db878435f3bd7ab67df8cbf6fe857336a2fe658350a3c6a0</Hash><FactVariable>Quantity</FactVariable><DimensionVariables><DimensionVariable>TradeAction</DimensionVariable><DimensionVariable>WeekDay</DimensionVariable></DimensionVariables><QueryScript>SELECT TradeAction,WeekDay, MAX(Quantity) as result FROM mergeview GROUP BY TradeAction,WeekDay</QueryScript><QueryLabel>System Genrerated</QueryLabel></Query><Query id="s130"><AggregateFunction>MAX</AggregateFunction><Hash>dcedfe2b5f8e350793632e2fa9495e62f19dbc77edd1cd6ab94a95d4709decaf</Hash><FactVariable>Price</FactVariable><DimensionVariables><DimensionVariable>TradeAction</DimensionVariable><DimensionVariable>WeekDay</DimensionVariable></DimensionVariables><QueryScript>SELECT TradeAction,WeekDay, MAX(Price) as result FROM mergeview GROUP BY TradeAction,WeekDay</QueryScript><QueryLabel>System Genrerated</QueryLabel></Query><Query id="s131"><AggregateFunction>SUM</AggregateFunction><Hash>d4fcfc2a8d57031e7bb339f6e04e99eb58f7f28141fe09fadeec63a552ad4835</Hash><FactVariable>Quantity</FactVariable><DimensionVariables><DimensionVariable>TickerSector</DimensionVariable><DimensionVariable>TradeAction</DimensionVariable><DimensionVariable>WeekDay</DimensionVariable></DimensionVariables><QueryScript>SELECT TickerSector,TradeAction,WeekDay, SUM(Quantity) as result FROM mergeview GROUP BY TickerSector,TradeAction,WeekDay</QueryScript><QueryLabel>System Genrerated</QueryLabel></Query><Query id="s132"><AggregateFunction>SUM</AggregateFunction><Hash>a58e553cc3897f1e7e36fd23bd52627f4b4ff16cc06086ee451e6fba05ab5387</Hash><FactVariable>Price</FactVariable><DimensionVariables><DimensionVariable>TickerSector</DimensionVariable><DimensionVariable>TradeAction</DimensionVariable><DimensionVariable>WeekDay</DimensionVariable></DimensionVariables><QueryScript>SELECT TickerSector,TradeAction,WeekDay, SUM(Price) as result FROM mergeview GROUP BY TickerSector,TradeAction,WeekDay</QueryScript><QueryLabel>System Genrerated</QueryLabel></Query><Query id="s133"><AggregateFunction>COUNT</AggregateFunction><Hash>b6642025c9735b858797972ff83397bceacfaac18197329f6213002d72cc222b</Hash><FactVariable>Quantity</FactVariable><DimensionVariables><DimensionVariable>TickerSector</DimensionVariable><DimensionVariable>TradeAction</DimensionVariable><DimensionVariable>WeekDay</DimensionVariable></DimensionVariables><QueryScript>SELECT TickerSector,TradeAction,WeekDay, COUNT(Quantity) as result FROM mergeview GROUP BY TickerSector,TradeAction,WeekDay</QueryScript><QueryLabel>System Genrerated</QueryLabel></Query><Query id="s134"><AggregateFunction>COUNT</AggregateFunction><Hash>09e231f142031748cf6e4d1c75c017ec4618700a93dc02fa75244087a3f3aca4</Hash><FactVariable>Price</FactVariable><DimensionVariables><DimensionVariable>TickerSector</DimensionVariable><DimensionVariable>TradeAction</DimensionVariable><DimensionVariable>WeekDay</DimensionVariable></DimensionVariables><QueryScript>SELECT TickerSector,TradeAction,WeekDay, COUNT(Price) as result FROM mergeview GROUP BY TickerSector,TradeAction,WeekDay</QueryScript><QueryLabel>System Genrerated</QueryLabel></Query><Query id="s135"><AggregateFunction>AVG</AggregateFunction><Hash>a9c3255d9db448eefba501f35480345b4a4856c3eada2777dbc2d7aeb6d15d25</Hash><FactVariable>Quantity</FactVariable><DimensionVariables><DimensionVariable>TickerSector</DimensionVariable><DimensionVariable>TradeAction</DimensionVariable><DimensionVariable>WeekDay</DimensionVariable></DimensionVariables><QueryScript>SELECT TickerSector,TradeAction,WeekDay, AVG(Quantity) as result FROM mergeview GROUP BY TickerSector,TradeAction,WeekDay</QueryScript><QueryLabel>System Genrerated</QueryLabel></Query><Query id="s136"><AggregateFunction>AVG</AggregateFunction><Hash>1cad1183e19b8e2bb92c236dd8e688e7a5534c648739a49fab128feb88a0da12</Hash><FactVariable>Price</FactVariable><DimensionVariables><DimensionVariable>TickerSector</DimensionVariable><DimensionVariable>TradeAction</DimensionVariable><DimensionVariable>WeekDay</DimensionVariable></DimensionVariables><QueryScript>SELECT TickerSector,TradeAction,WeekDay, AVG(Price) as result FROM mergeview GROUP BY TickerSector,TradeAction,WeekDay</QueryScript><QueryLabel>System Genrerated</QueryLabel></Query><Query id="s137"><AggregateFunction>MIN</AggregateFunction><Hash>4eb10ddaa0e086abc0a640bed901643404db54d5485e77dc97fee7b68258f257</Hash><FactVariable>Quantity</FactVariable><DimensionVariables><DimensionVariable>TickerSector</DimensionVariable><DimensionVariable>TradeAction</DimensionVariable><DimensionVariable>WeekDay</DimensionVariable></DimensionVariables><QueryScript>SELECT TickerSector,TradeAction,WeekDay, MIN(Quantity) as result FROM mergeview GROUP BY TickerSector,TradeAction,WeekDay</QueryScript><QueryLabel>System Genrerated</QueryLabel></Query><Query id="s138"><AggregateFunction>MIN</AggregateFunction><Hash>81e72f977b0694f514a27d5443258483436b7f6e160756b6ca7213eafbf073b6</Hash><FactVariable>Price</FactVariable><DimensionVariables><DimensionVariable>TickerSector</DimensionVariable><DimensionVariable>TradeAction</DimensionVariable><DimensionVariable>WeekDay</DimensionVariable></DimensionVariables><QueryScript>SELECT TickerSector,TradeAction,WeekDay, MIN(Price) as result FROM mergeview GROUP BY TickerSector,TradeAction,WeekDay</QueryScript><QueryLabel>System Genrerated</QueryLabel></Query><Query id="s139"><AggregateFunction>MAX</AggregateFunction><Hash>4d700dcbdc01529da322b334932a04104203dec36eee2b20dbb076bba54f6a85</Hash><FactVariable>Quantity</FactVariable><DimensionVariables><DimensionVariable>TickerSector</DimensionVariable><DimensionVariable>TradeAction</DimensionVariable><DimensionVariable>WeekDay</DimensionVariable></DimensionVariables><QueryScript>SELECT TickerSector,TradeAction,WeekDay, MAX(Quantity) as result FROM mergeview GROUP BY TickerSector,TradeAction,WeekDay</QueryScript><QueryLabel>System Genrerated</QueryLabel></Query><Query id="s140"><AggregateFunction>MAX</AggregateFunction><Hash>a2ac52b118ff431bb8c714fb6e227450183e72b653da3633e48e12a1312788d0</Hash><FactVariable>Price</FactVariable><DimensionVariables><DimensionVariable>TickerSector</DimensionVariable><DimensionVariable>TradeAction</DimensionVariable><DimensionVariable>WeekDay</DimensionVariable></DimensionVariables><QueryScript>SELECT TickerSector,TradeAction,WeekDay, MAX(Price) as result FROM mergeview GROUP BY TickerSector,TradeAction,WeekDay</QueryScript><QueryLabel>System Genrerated</QueryLabel></Query><Query id="s141"><AggregateFunction>SUM</AggregateFunction><Hash>83953c68756ba7d80c4d9676e3f798021df750fbdaf2d6c371a4207af70cd444</Hash><FactVariable>Quantity</FactVariable><DimensionVariables><DimensionVariable>TickerSymbol</DimensionVariable><DimensionVariable>TradeAction</DimensionVariable><DimensionVariable>WeekDay</DimensionVariable></DimensionVariables><QueryScript>SELECT TickerSymbol,TradeAction,WeekDay, SUM(Quantity) as result FROM mergeview GROUP BY TickerSymbol,TradeAction,WeekDay</QueryScript><QueryLabel>System Genrerated</QueryLabel></Query><Query id="s142"><AggregateFunction>SUM</AggregateFunction><Hash>acc6f8f218551a47b5524db94f35204fcadf27d954d81c335bae5622672789a5</Hash><FactVariable>Price</FactVariable><DimensionVariables><DimensionVariable>TickerSymbol</DimensionVariable><DimensionVariable>TradeAction</DimensionVariable><DimensionVariable>WeekDay</DimensionVariable></DimensionVariables><QueryScript>SELECT TickerSymbol,TradeAction,WeekDay, SUM(Price) as result FROM mergeview GROUP BY TickerSymbol,TradeAction,WeekDay</QueryScript><QueryLabel>System Genrerated</QueryLabel></Query><Query id="s143"><AggregateFunction>COUNT</AggregateFunction><Hash>49412bcfd1f17a512295e1c296f8270fbba43db5e87d8c5e47b7a74d5f4da559</Hash><FactVariable>Quantity</FactVariable><DimensionVariables><DimensionVariable>TickerSymbol</DimensionVariable><DimensionVariable>TradeAction</DimensionVariable><DimensionVariable>WeekDay</DimensionVariable></DimensionVariables><QueryScript>SELECT TickerSymbol,TradeAction,WeekDay, COUNT(Quantity) as result FROM mergeview GROUP BY TickerSymbol,TradeAction,WeekDay</QueryScript><QueryLabel>System Genrerated</QueryLabel></Query><Query id="s144"><AggregateFunction>COUNT</AggregateFunction><Hash>78c7f2b0b11dfc14ff300ce2bf4f14b504c4bd54292c1e1fa59cf8248d168a13</Hash><FactVariable>Price</FactVariable><DimensionVariables><DimensionVariable>TickerSymbol</DimensionVariable><DimensionVariable>TradeAction</DimensionVariable><DimensionVariable>WeekDay</DimensionVariable></DimensionVariables><QueryScript>SELECT TickerSymbol,TradeAction,WeekDay, COUNT(Price) as result FROM mergeview GROUP BY TickerSymbol,TradeAction,WeekDay</QueryScript><QueryLabel>System Genrerated</QueryLabel></Query><Query id="s145"><AggregateFunction>AVG</AggregateFunction><Hash>94b4fa72bfbd445cc79c0f3aa8ce1a944dbaed3578b1d64bd1ec6308a11a4850</Hash><FactVariable>Quantity</FactVariable><DimensionVariables><DimensionVariable>TickerSymbol</DimensionVariable><DimensionVariable>TradeAction</DimensionVariable><DimensionVariable>WeekDay</DimensionVariable></DimensionVariables><QueryScript>SELECT TickerSymbol,TradeAction,WeekDay, AVG(Quantity) as result FROM mergeview GROUP BY TickerSymbol,TradeAction,WeekDay</QueryScript><QueryLabel>System Genrerated</QueryLabel></Query><Query id="s146"><AggregateFunction>AVG</AggregateFunction><Hash>ec869a6bcf24affc0b423d8eb15798968d76de208a97c74662fe8734fd2d6f47</Hash><FactVariable>Price</FactVariable><DimensionVariables><DimensionVariable>TickerSymbol</DimensionVariable><DimensionVariable>TradeAction</DimensionVariable><DimensionVariable>WeekDay</DimensionVariable></DimensionVariables><QueryScript>SELECT TickerSymbol,TradeAction,WeekDay, AVG(Price) as result FROM mergeview GROUP BY TickerSymbol,TradeAction,WeekDay</QueryScript><QueryLabel>System Genrerated</QueryLabel></Query><Query id="s147"><AggregateFunction>MIN</AggregateFunction><Hash>db5e5255179cda2d2f67b13c90da01df26534bf5f103f9a6ca44f7f575c80dad</Hash><FactVariable>Quantity</FactVariable><DimensionVariables><DimensionVariable>TickerSymbol</DimensionVariable><DimensionVariable>TradeAction</DimensionVariable><DimensionVariable>WeekDay</DimensionVariable></DimensionVariables><QueryScript>SELECT TickerSymbol,TradeAction,WeekDay, MIN(Quantity) as result FROM mergeview GROUP BY TickerSymbol,TradeAction,WeekDay</QueryScript><QueryLabel>System Genrerated</QueryLabel></Query><Query id="s148"><AggregateFunction>MIN</AggregateFunction><Hash>ef849cd7eb28cda1f2b05fbd20f5f3906170f900d71c467c2bd8f88c606a30e5</Hash><FactVariable>Price</FactVariable><DimensionVariables><DimensionVariable>TickerSymbol</DimensionVariable><DimensionVariable>TradeAction</DimensionVariable><DimensionVariable>WeekDay</DimensionVariable></DimensionVariables><QueryScript>SELECT TickerSymbol,TradeAction,WeekDay, MIN(Price) as result FROM mergeview GROUP BY TickerSymbol,TradeAction,WeekDay</QueryScript><QueryLabel>System Genrerated</QueryLabel></Query><Query id="s149"><AggregateFunction>MAX</AggregateFunction><Hash>18ff6bb03d1438c606f30fb498d017b7bdb4b96e7fcb1e8bf7a5849dc1779c7e</Hash><FactVariable>Quantity</FactVariable><DimensionVariables><DimensionVariable>TickerSymbol</DimensionVariable><DimensionVariable>TradeAction</DimensionVariable><DimensionVariable>WeekDay</DimensionVariable></DimensionVariables><QueryScript>SELECT TickerSymbol,TradeAction,WeekDay, MAX(Quantity) as result FROM mergeview GROUP BY TickerSymbol,TradeAction,WeekDay</QueryScript><QueryLabel>System Genrerated</QueryLabel></Query><Query id="s150"><AggregateFunction>MAX</AggregateFunction><Hash>25569ffccce363c4682b6f59aa1d39421ead38fba3d8a578e8a7754b7fa0c4a4</Hash><FactVariable>Price</FactVariable><DimensionVariables><DimensionVariable>TickerSymbol</DimensionVariable><DimensionVariable>TradeAction</DimensionVariable><DimensionVariable>WeekDay</DimensionVariable></DimensionVariables><QueryScript>SELECT TickerSymbol,TradeAction,WeekDay, MAX(Price) as result FROM mergeview GROUP BY TickerSymbol,TradeAction,WeekDay</QueryScript><QueryLabel>System Genrerated</QueryLabel></Query><Query id="s151"><AggregateFunction>SUM</AggregateFunction><Hash>05ffe605650d5843210144aeb0756b027307ba567763a5a6a40feb799fdce7d1</Hash><FactVariable>Quantity</FactVariable><DimensionVariables><DimensionVariable>TickerSector</DimensionVariable><DimensionVariable>TickerSymbol</DimensionVariable><DimensionVariable>TradeAction</DimensionVariable><DimensionVariable>WeekDay</DimensionVariable></DimensionVariables><QueryScript>SELECT TickerSector,TickerSymbol,TradeAction,WeekDay, SUM(Quantity) as result FROM mergeview GROUP BY TickerSector,TickerSymbol,TradeAction,WeekDay</QueryScript><QueryLabel>System Genrerated</QueryLabel></Query><Query id="s152"><AggregateFunction>SUM</AggregateFunction><Hash>90fdebbaa0664d75f925d8c937c469aa59fa03e4de750c9c02cc2c550e5bda1e</Hash><FactVariable>Price</FactVariable><DimensionVariables><DimensionVariable>TickerSector</DimensionVariable><DimensionVariable>TickerSymbol</DimensionVariable><DimensionVariable>TradeAction</DimensionVariable><DimensionVariable>WeekDay</DimensionVariable></DimensionVariables><QueryScript>SELECT TickerSector,TickerSymbol,TradeAction,WeekDay, SUM(Price) as result FROM mergeview GROUP BY TickerSector,TickerSymbol,TradeAction,WeekDay</QueryScript><QueryLabel>System Genrerated</QueryLabel></Query><Query id="s153"><AggregateFunction>COUNT</AggregateFunction><Hash>8746e424b60e45c09412e80efa6cd7211be3cf91635cdd0024d3c7cf4bb0e96c</Hash><FactVariable>Quantity</FactVariable><DimensionVariables><DimensionVariable>TickerSector</DimensionVariable><DimensionVariable>TickerSymbol</DimensionVariable><DimensionVariable>TradeAction</DimensionVariable><DimensionVariable>WeekDay</DimensionVariable></DimensionVariables><QueryScript>SELECT TickerSector,TickerSymbol,TradeAction,WeekDay, COUNT(Quantity) as result FROM mergeview GROUP BY TickerSector,TickerSymbol,TradeAction,WeekDay</QueryScript><QueryLabel>System Genrerated</QueryLabel></Query><Query id="s154"><AggregateFunction>COUNT</AggregateFunction><Hash>639fa046a50cc0f43c13e09cf1de630b32767310d1c4b5f9eed7528446169791</Hash><FactVariable>Price</FactVariable><DimensionVariables><DimensionVariable>TickerSector</DimensionVariable><DimensionVariable>TickerSymbol</DimensionVariable><DimensionVariable>TradeAction</DimensionVariable><DimensionVariable>WeekDay</DimensionVariable></DimensionVariables><QueryScript>SELECT TickerSector,TickerSymbol,TradeAction,WeekDay, COUNT(Price) as result FROM mergeview GROUP BY TickerSector,TickerSymbol,TradeAction,WeekDay</QueryScript><QueryLabel>System Genrerated</QueryLabel></Query><Query id="s155"><AggregateFunction>AVG</AggregateFunction><Hash>88896f74d781366106412bb565f8df61bec836ddd0a8b9a4e305a288b207d525</Hash><FactVariable>Quantity</FactVariable><DimensionVariables><DimensionVariable>TickerSector</DimensionVariable><DimensionVariable>TickerSymbol</DimensionVariable><DimensionVariable>TradeAction</DimensionVariable><DimensionVariable>WeekDay</DimensionVariable></DimensionVariables><QueryScript>SELECT TickerSector,TickerSymbol,TradeAction,WeekDay, AVG(Quantity) as result FROM mergeview GROUP BY TickerSector,TickerSymbol,TradeAction,WeekDay</QueryScript><QueryLabel>System Genrerated</QueryLabel></Query><Query id="s156"><AggregateFunction>AVG</AggregateFunction><Hash>0de864ecd6188e417097bb8a560f037811a0e4b1b2550bd76a80675ebda945d6</Hash><FactVariable>Price</FactVariable><DimensionVariables><DimensionVariable>TickerSector</DimensionVariable><DimensionVariable>TickerSymbol</DimensionVariable><DimensionVariable>TradeAction</DimensionVariable><DimensionVariable>WeekDay</DimensionVariable></DimensionVariables><QueryScript>SELECT TickerSector,TickerSymbol,TradeAction,WeekDay, AVG(Price) as result FROM mergeview GROUP BY TickerSector,TickerSymbol,TradeAction,WeekDay</QueryScript><QueryLabel>System Genrerated</QueryLabel></Query><Query id="s157"><AggregateFunction>MIN</AggregateFunction><Hash>c5e553242720a9d4db48159f9fc5bf1cff31ef801e2c690f2fac402b9f8ec6db</Hash><FactVariable>Quantity</FactVariable><DimensionVariables><DimensionVariable>TickerSector</DimensionVariable><DimensionVariable>TickerSymbol</DimensionVariable><DimensionVariable>TradeAction</DimensionVariable><DimensionVariable>WeekDay</DimensionVariable></DimensionVariables><QueryScript>SELECT TickerSector,TickerSymbol,TradeAction,WeekDay, MIN(Quantity) as result FROM mergeview GROUP BY TickerSector,TickerSymbol,TradeAction,WeekDay</QueryScript><QueryLabel>System Genrerated</QueryLabel></Query><Query id="s158"><AggregateFunction>MIN</AggregateFunction><Hash>4b696b79c36e7f7046556a75f9a6a83cd1c0ddc46dd2e3257ff929dc83824a0f</Hash><FactVariable>Price</FactVariable><DimensionVariables><DimensionVariable>TickerSector</DimensionVariable><DimensionVariable>TickerSymbol</DimensionVariable><DimensionVariable>TradeAction</DimensionVariable><DimensionVariable>WeekDay</DimensionVariable></DimensionVariables><QueryScript>SELECT TickerSector,TickerSymbol,TradeAction,WeekDay, MIN(Price) as result FROM mergeview GROUP BY TickerSector,TickerSymbol,TradeAction,WeekDay</QueryScript><QueryLabel>System Genrerated</QueryLabel></Query><Query id="s159"><AggregateFunction>MAX</AggregateFunction><Hash>72fd06d8605595c19f03f792ff45dc89d44450786f34143791c83d38670f21d0</Hash><FactVariable>Quantity</FactVariable><DimensionVariables><DimensionVariable>TickerSector</DimensionVariable><DimensionVariable>TickerSymbol</DimensionVariable><DimensionVariable>TradeAction</DimensionVariable><DimensionVariable>WeekDay</DimensionVariable></DimensionVariables><QueryScript>SELECT TickerSector,TickerSymbol,TradeAction,WeekDay, MAX(Quantity) as result FROM mergeview GROUP BY TickerSector,TickerSymbol,TradeAction,WeekDay</QueryScript><QueryLabel>System Genrerated</QueryLabel></Query><Query id="s160"><AggregateFunction>MAX</AggregateFunction><Hash>7713a86b765b0821d541b4bf1ebea2d75d7013f32314f47045ef080f531eb749</Hash><FactVariable>Price</FactVariable><DimensionVariables><DimensionVariable>TickerSector</DimensionVariable><DimensionVariable>TickerSymbol</DimensionVariable><DimensionVariable>TradeAction</DimensionVariable><DimensionVariable>WeekDay</DimensionVariable></DimensionVariables><QueryScript>SELECT TickerSector,TickerSymbol,TradeAction,WeekDay, MAX(Price) as result FROM mergeview GROUP BY TickerSector,TickerSymbol,TradeAction,WeekDay</QueryScript><QueryLabel>System Genrerated</QueryLabel></Query></Queries>